brinicle/__init__.py
brinicle/_brinicle.cpython-314-x86_64-linux-gnu.so
brinicle/ref/api.py
brinicle/ref/client.py
brinicle/ref/io_models.py
brinicle/src/bindings.cpp
brinicle/src/hnsw.h
brinicle/src/hnsw_manager.h
brinicle/src/knn.h
brinicle/src/operations.h
brinicle.libs/libgomp-e985bcbb.so.1.0.0
brinicle-0.0.4.dist-info/METADATA
brinicle-0.0.4.dist-info/WHEEL
brinicle-0.0.4.dist-info/RECORD
brinicle-0.0.4.dist-info/licenses/LICENSE
brinicle-0.0.4.dist-info/sboms/auditwheel.cdx.json
