Metadata-Version: 2.2
Name: brinicle
Version: 0.0.4
Summary: brinicle is a C++ vector index engine (ANN library) optimized for disk-first, low-RAM similarity search.
Keywords: brinicle,vector,retrieval,RAG,bicardinal
Author-Email: bicardinal <support@bicardinal.com>
License: Apache-2.0
Classifier: Intended Audience :: Developers
Classifier: Intended Audience :: Information Technology
Classifier: Intended Audience :: Science/Research
Classifier: Intended Audience :: System Administrators
Classifier: Operating System :: OS Independent
Classifier: Programming Language :: Python :: 3
Classifier: Programming Language :: Python :: 3.10
Classifier: Programming Language :: Python :: 3.11
Classifier: Programming Language :: Python :: 3.12
Classifier: Programming Language :: Python :: 3.13
Classifier: Programming Language :: Python :: 3.14
Classifier: Topic :: Database
Classifier: Topic :: Software Development :: Libraries :: Python Modules
Project-URL: Homepage, https://github.com/bicardinal/brinicle
Project-URL: Issues, https://github.com/bicardinal/brinicle/issues
Requires-Python: >=3.10
Provides-Extra: server
Requires-Dist: fastapi; extra == "server"
Requires-Dist: uvicorn[standard]; extra == "server"
Requires-Dist: pydantic; extra == "server"
Requires-Dist: python-multipart; extra == "server"
Requires-Dist: orjson; extra == "server"
Requires-Dist: numpy; extra == "server"
